stepcounter-1.0.7.dist-info/WHEEL
stepcounter-1.0.7.dist-info/top_level.txt
stepcounter-1.0.7.dist-info/LICENSE
stepcounter-1.0.7.dist-info/METADATA
stepcounter-1.0.7.dist-info/entry_points.txt
stepcounter-1.0.7.dist-info/RECORD
example/x.py
example/gcd.py
example/example.py
example/__init__.py
src/__init__.py
src/profiler/__init__.py
src/profiler/profiler.py
src/parser/parser.py
src/parser/__init__.py
src/step_counting/__main__.py
src/step_counting/non_builtin_types.py
src/step_counting/setup_recording.py
src/step_counting/utils.py
src/step_counting/ignor.py
src/step_counting/__init__.py
src/step_counting/ib111_restrictions.py
src/step_counting/original_methods.py
src/step_counting/patch/patching.py
src/step_counting/patch/method_switch.py
src/step_counting/patch/__init__.py
src/step_counting/patch/py_object.py
src/step_counting/patch/patch_imports.py
src/step_counting/patch/bin/patchdictionary.cpython-310-x86_64-linux-gnu.so
src/step_counting/patch/bin/patchlist.cpython-310-x86_64-linux-gnu.so
src/step_counting/patch/bin/patchtuple.cpython-310-x86_64-linux-gnu.so
src/step_counting/patch/bin/patchstr.cpython-310-x86_64-linux-gnu.so
src/step_counting/patch/bin/patchbytearray.cpython-310-x86_64-linux-gnu.so
src/step_counting/patch/bin/__init__.py
src/step_counting/patch/c_modules/__init__.py
src/step_counting/utils/module.py
src/step_counting/utils/__init__.py
src/step_counting/utils/methods.py
src/step_counting/profiler/__init__.py
src/step_counting/profiler/profiler.py
src/step_counting/parser/parser.py
src/step_counting/parser/__init__.py
src/step_counting/decorator/utils.py
src/step_counting/decorator/__init__.py
src/step_counting/decorator/decorators.py
src/step_counting/decorator/evaluations/complexities.py
src/step_counting/decorator/evaluations/evaluations.py
src/step_counting/decorator/evaluations/__init__.py
src/step_counting/decorator/evaluations/builtins/complex_evaluations.py
src/step_counting/decorator/evaluations/builtins/memoryview_evaluations.py
src/step_counting/decorator/evaluations/builtins/str_evaluations.py
src/step_counting/decorator/evaluations/builtins/dict_keys_evaluations.py
